versionmanagerpy/__init__.py
versionmanagerpy/event.py
versionmanagerpy/local.py
versionmanagerpy/project.py
versionmanagerpy/remote.py
versionmanagerpy/version.py
versionmanagerpy/versionmanager.py
versionmanagerpy-1.0.2.dist-info/LICENSE
versionmanagerpy-1.0.2.dist-info/METADATA
versionmanagerpy-1.0.2.dist-info/WHEEL
versionmanagerpy-1.0.2.dist-info/top_level.txt
versionmanagerpy-1.0.2.dist-info/RECORD
